Workbook

Sheet Instructions
A1: Income Tax Lookup Assignment — Advanced
A2: This assignment has TWO working sheets. On 'Tax Worksheet' you auto-fill a 12-employee payroll table. On 'Questions' you answer 18 lookup tasks. Everything must be done with formulas — no typed answers, no manual arithmetic. Tax rules: New Regime, FY 2024-25 (AY 2025-26).
A4: Part A — Tax Worksheet (auto-fill columns G–L for all 12 employees)
A5: Column | B5: Compute | C5: Function | D5: Marks
A6: G Taxable | B6: Gross − Standard Deduction (min 0) | C6: MAX + absolute ref | D6: 2
A7: H Slab Rate | B7: Marginal rate for the taxable income | C7: VLOOKUP (TRUE) | D7: 2
A8: I Slab Label | B8: Slab name | C8: INDEX + MATCH (1) | D8: 2
A9: J Income Tax | B9: Progressive tax: tax-at-band-start + excess×rate | C9: VLOOKUP (TRUE) nested | D9: 4
A10: K Rebate 87A | B10: If taxable ≤ ₹7L, min(tax, ₹25,000), else 0 | C10: IF + MIN + refs | D10: 3
A11: L Tax After Rebate | B11: Income Tax − Rebate | C11: Subtraction | D11: 1
A12: Part A subtotal | D12: 14
A14: Part B — Questions sheet (18 tasks)
A15: 18 questions covering XLOOKUP, VLOOKUP, HLOOKUP, INDEX, MATCH and combinations (two-way lookup, reverse lookup, nested lookups, plus COUNTIF / SUMIF / MAX helpers). Worth 51 marks.
A17: GRAND TOTAL: 65 marks
A19: Colour key: PEACH = write your formula here • BLUE = input/key cells • GREEN = lookup-key columns. Rules: exact match (FALSE/0) for EmpID, Name, Department, City; approximate match (TRUE/1) only for income→slab and income→surcharge. Use ABSOLUTE ($) references to all reference tables. The progressive-tax method uses the 'Tax at Band Start' column so a single set of VLOOKUPs gives the full tax.
A21: Name: ______________________ Roll No: __________ Date: __________

Sheet Tax Worksheet
A1: Income Tax Auto-Fill — Advanced Worksheet
A2: New Regime, FY 2024-25 (AY 2025-26). Fill every PEACH cell with a lookup-based formula. Reference tables are to the right (columns from N). Use absolute ($) refs so formulas copy down.
A4: EmpID | B4: Name | C4: Dept | D4: Gender | E4: City | F4: Gross (₹) | G4: Taxable (₹) | H4: Slab Rate | I4: Slab Label | J4: Income Tax (₹) | K4: Rebate 87A (₹) | L4: Tax After Rebate (₹) | N4: Slab Table (progressive) — New Regime FY 2024-25
A5: E101 | B5: Aarav Sharma | C5: Engineering | D5: M | E5: Bangalore | F5: 1850000 | G5: =MAX(F5-$O$22,0) | H5: =VLOOKUP(G5,$N$6:$Q$11,2,TRUE) | I5: =INDEX($P$6:$P$11,MATCH(G5,$N$6:$N$11,1)) | J5: =VLOOKUP(G5,$N$6:$Q$11,4,TRUE)+(G5-VLOOKUP(G5,$N$6:$Q$11,1,TRUE))*VLOOKUP(G5,$N$6:$Q$11,2,TRUE) | K5: =IF(G5<=$O$24,MIN(J5,$O$25),0) | L5: =J5-K5 | N5: Income From (₹) | O5: Rate | P5: Label | Q5: Tax at Band Start (₹)
A6: E102 | B6: Diya Patel | C6: Sales | D6: F | E6: Mumbai | F6: 680000 | G6: =MAX(F6-$O$22,0) | H6: =VLOOKUP(G6,$N$6:$Q$11,2,TRUE) | I6: =INDEX($P$6:$P$11,MATCH(G6,$N$6:$N$11,1)) | J6: =VLOOKUP(G6,$N$6:$Q$11,4,TRUE)+(G6-VLOOKUP(G6,$N$6:$Q$11,1,TRUE))*VLOOKUP(G6,$N$6:$Q$11,2,TRUE) | K6: =IF(G6<=$O$24,MIN(J6,$O$25),0) | L6: =J6-K6 | N6: 0 | O6: 0 | P6: Nil | Q6: 0
A7: E103 | B7: Vihaan Reddy | C7: Marketing | D7: M | E7: Hyderabad | F7: 1120000 | G7: =MAX(F7-$O$22,0) | H7: =VLOOKUP(G7,$N$6:$Q$11,2,TRUE) | I7: =INDEX($P$6:$P$11,MATCH(G7,$N$6:$N$11,1)) | J7: =VLOOKUP(G7,$N$6:$Q$11,4,TRUE)+(G7-VLOOKUP(G7,$N$6:$Q$11,1,TRUE))*VLOOKUP(G7,$N$6:$Q$11,2,TRUE) | K7: =IF(G7<=$O$24,MIN(J7,$O$25),0) | L7: =J7-K7 | N7: 300000 | O7: 0.05 | P7: 5% | Q7: 0
A8: E104 | B8: Ananya Iyer | C8: Finance | D8: F | E8: Chennai | F8: 1380000 | G8: =MAX(F8-$O$22,0) | H8: =VLOOKUP(G8,$N$6:$Q$11,2,TRUE) | I8: =INDEX($P$6:$P$11,MATCH(G8,$N$6:$N$11,1)) | J8: =VLOOKUP(G8,$N$6:$Q$11,4,TRUE)+(G8-VLOOKUP(G8,$N$6:$Q$11,1,TRUE))*VLOOKUP(G8,$N$6:$Q$11,2,TRUE) | K8: =IF(G8<=$O$24,MIN(J8,$O$25),0) | L8: =J8-K8 | N8: 700000 | O8: 0.1 | P8: 10% | Q8: 20000
A9: E105 | B9: Kabir Nair | C9: Engineering | D9: M | E9: Bangalore | F9: 6200000 | G9: =MAX(F9-$O$22,0) | H9: =VLOOKUP(G9,$N$6:$Q$11,2,TRUE) | I9: =INDEX($P$6:$P$11,MATCH(G9,$N$6:$N$11,1)) | J9: =VLOOKUP(G9,$N$6:$Q$11,4,TRUE)+(G9-VLOOKUP(G9,$N$6:$Q$11,1,TRUE))*VLOOKUP(G9,$N$6:$Q$11,2,TRUE) | K9: =IF(G9<=$O$24,MIN(J9,$O$25),0) | L9: =J9-K9 | N9: 1000000 | O9: 0.15 | P9: 15% | Q9: 50000
A10: E106 | B10: Ishaan Gupta | C10: Sales | D10: M | E10: Delhi | F10: 520000 | G10: =MAX(F10-$O$22,0) | H10: =VLOOKUP(G10,$N$6:$Q$11,2,TRUE) | I10: =INDEX($P$6:$P$11,MATCH(G10,$N$6:$N$11,1)) | J10: =VLOOKUP(G10,$N$6:$Q$11,4,TRUE)+(G10-VLOOKUP(G10,$N$6:$Q$11,1,TRUE))*VLOOKUP(G10,$N$6:$Q$11,2,TRUE) | K10: =IF(G10<=$O$24,MIN(J10,$O$25),0) | L10: =J10-K10 | N10: 1200000 | O10: 0.2 | P10: 20% | Q10: 80000
A11: E107 | B11: Saanvi Rao | C11: HR | D11: F | E11: Pune | F11: 940000 | G11: =MAX(F11-$O$22,0) | H11: =VLOOKUP(G11,$N$6:$Q$11,2,TRUE) | I11: =INDEX($P$6:$P$11,MATCH(G11,$N$6:$N$11,1)) | J11: =VLOOKUP(G11,$N$6:$Q$11,4,TRUE)+(G11-VLOOKUP(G11,$N$6:$Q$11,1,TRUE))*VLOOKUP(G11,$N$6:$Q$11,2,TRUE) | K11: =IF(G11<=$O$24,MIN(J11,$O$25),0) | L11: =J11-K11 | N11: 1500000 | O11: 0.3 | P11: 30% | Q11: 140000
A12: E108 | B12: Arjun Mehta | C12: Finance | D12: M | E12: Mumbai | F12: 760000 | G12: =MAX(F12-$O$22,0) | H12: =VLOOKUP(G12,$N$6:$Q$11,2,TRUE) | I12: =INDEX($P$6:$P$11,MATCH(G12,$N$6:$N$11,1)) | J12: =VLOOKUP(G12,$N$6:$Q$11,4,TRUE)+(G12-VLOOKUP(G12,$N$6:$Q$11,1,TRUE))*VLOOKUP(G12,$N$6:$Q$11,2,TRUE) | K12: =IF(G12<=$O$24,MIN(J12,$O$25),0) | L12: =J12-K12
A13: E109 | B13: Myra Joshi | C13: Marketing | D13: F | E13: Delhi | F13: 1610000 | G13: =MAX(F13-$O$22,0) | H13: =VLOOKUP(G13,$N$6:$Q$11,2,TRUE) | I13: =INDEX($P$6:$P$11,MATCH(G13,$N$6:$N$11,1)) | J13: =VLOOKUP(G13,$N$6:$Q$11,4,TRUE)+(G13-VLOOKUP(G13,$N$6:$Q$11,1,TRUE))*VLOOKUP(G13,$N$6:$Q$11,2,TRUE) | K13: =IF(G13<=$O$24,MIN(J13,$O$25),0) | L13: =J13-K13
A14: E110 | B14: Reyansh Das | C14: Engineering | D14: M | E14: Kolkata | F14: 360000 | G14: =MAX(F14-$O$22,0) | H14: =VLOOKUP(G14,$N$6:$Q$11,2,TRUE) | I14: =INDEX($P$6:$P$11,MATCH(G14,$N$6:$N$11,1)) | J14: =VLOOKUP(G14,$N$6:$Q$11,4,TRUE)+(G14-VLOOKUP(G14,$N$6:$Q$11,1,TRUE))*VLOOKUP(G14,$N$6:$Q$11,2,TRUE) | K14: =IF(G14<=$O$24,MIN(J14,$O$25),0) | L14: =J14-K14 | N14: Surcharge Table (on tax)
A15: E111 | B15: Aditya Menon | C15: Finance | D15: M | E15: Chennai | F15: 11500000 | G15: =MAX(F15-$O$22,0) | H15: =VLOOKUP(G15,$N$6:$Q$11,2,TRUE) | I15: =INDEX($P$6:$P$11,MATCH(G15,$N$6:$N$11,1)) | J15: =VLOOKUP(G15,$N$6:$Q$11,4,TRUE)+(G15-VLOOKUP(G15,$N$6:$Q$11,1,TRUE))*VLOOKUP(G15,$N$6:$Q$11,2,TRUE) | K15: =IF(G15<=$O$24,MIN(J15,$O$25),0) | L15: =J15-K15 | N15: Total Income From (₹) | O15: Surcharge
A16: E112 | B16: Kiara Shah | C16: Sales | D16: F | E16: Mumbai | F16: 2750000 | G16: =MAX(F16-$O$22,0) | H16: =VLOOKUP(G16,$N$6:$Q$11,2,TRUE) | I16: =INDEX($P$6:$P$11,MATCH(G16,$N$6:$N$11,1)) | J16: =VLOOKUP(G16,$N$6:$Q$11,4,TRUE)+(G16-VLOOKUP(G16,$N$6:$Q$11,1,TRUE))*VLOOKUP(G16,$N$6:$Q$11,2,TRUE) | K16: =IF(G16<=$O$24,MIN(J16,$O$25),0) | L16: =J16-K16 | N16: 0 | O16: 0
N17: 5000000 | O17: 0.1
N18: 10000000 | O18: 0.15
N19: 20000000 | O19: 0.25
N21: Constants
N22: Standard Deduction (₹) | O22: 75000
N23: Health & Education Cess | O23: 0.04
N24: 87A Rebate Income Limit (₹) | O24: 700000
N25: 87A Max Rebate (₹) | O25: 25000
N27: Department Directory (horizontal — for HLOOKUP)
N28: Department | O28: Engineering | P28: Sales | Q28: Marketing | R28: Finance | S28: HR
N29: HR Email | O29: hr.eng@co.in | P29: hr.sales@co.in | Q29: hr.mktg@co.in | R29: hr.fin@co.in | S29: hr.hr@co.in
N30: HR Head | O30: R. Banerjee | P30: S. Krishnan | Q30: P. Desai | R30: M. Joshi | S30: N. Verma
N32: City Classification
N33: City | O33: Class
N34: Mumbai | O34: Metro
N35: Delhi | O35: Metro
N36: Bangalore | O36: Metro
N37: Chennai | O37: Metro
N38: Hyderabad | O38: Non-Metro
N39: Pune | O39: Non-Metro
N40: Kolkata | O40: Metro

Sheet Questions
A1: Questions
A2: Answer in the PEACH cells using lookup functions (XLOOKUP / VLOOKUP / HLOOKUP / INDEX / MATCH) and the tables on 'Tax Worksheet'. Type the EmpID or value into the blue input where one is given.
A4: Inputs you may change:
A5: EmpID #1 | B5: E105
A6: EmpID #2 | B6: E111
A7: Department | B7: Finance
A8: City | B8: Pune
A9: Income to test (₹) | B9: 1350000
A10: Field name (for Q13) | B10: City
A11: Name (for Q17) | B11: Kiara Shah
A13: # | B13: Question / Task | C13: Function(s) to use | D13: Your Answer | E13: Marks
A14: 1 | B14: Look up the Name of EmpID #1 (B5). | C14: XLOOKUP | D14: =XLOOKUP($B$5,'Tax Worksheet'!$A$5:$A$16,'Tax Worksheet'!$B$5:$B$16) | E14: 2
A15: 2 | B15: Look up the Department of EmpID #1 using VLOOKUP (column index). | C15: VLOOKUP | D15: =VLOOKUP($B$5,'Tax Worksheet'!$A$5:$L$16,3,FALSE) | E15: 2
A16: 3 | B16: Look up the Gross Salary of EmpID #2 (B6) using INDEX + MATCH. | C16: INDEX, MATCH | D16: =INDEX('Tax Worksheet'!$F$5:$F$16,MATCH($B$6,'Tax Worksheet'!$A$5:$A$16,0)) | E16: 3
A17: 4 | B17: Get the HR Email for the Department in B7 (horizontal directory). | C17: HLOOKUP | D17: =HLOOKUP($B$7,'Tax Worksheet'!$N$28:$S$30,2,FALSE) | E17: 3
A18: 5 | B18: Get the HR Head for the Department in B7 (3rd row of directory). | C18: HLOOKUP | D18: =HLOOKUP($B$7,'Tax Worksheet'!$N$28:$S$30,3,FALSE) | E18: 2
A19: 6 | B19: Classify the City in B8 as Metro / Non-Metro. | C19: VLOOKUP | D19: =VLOOKUP($B$8,'Tax Worksheet'!$N$33:$O$40,2,FALSE) | E19: 2
A20: 7 | B20: For the income in B9, find the marginal Slab Rate (approximate match). | C20: VLOOKUP (TRUE) | D20: =VLOOKUP($B$9,'Tax Worksheet'!$N$6:$Q$11,2,TRUE) | E20: 3
A21: 8 | B21: For the income in B9, return the Slab Label using INDEX + MATCH (match type 1). | C21: INDEX, MATCH | D21: =INDEX('Tax Worksheet'!$P$6:$P$11,MATCH($B$9,'Tax Worksheet'!$N$6:$N$11,1)) | E21: 3
A22: 9 | B22: For the income in B9, compute progressive Income Tax (tax-at-band-start + excess × rate). | C22: VLOOKUP (TRUE) ×3 | D22: =VLOOKUP($B$9,'Tax Worksheet'!$N$6:$Q$11,4,TRUE)+($B$9-VLOOKUP($B$9,'Tax Worksheet'!$N$6:$Q$11,1,TRUE))*VLOOKUP($B$9,'Tax Worksheet'!$N$6:$Q$11,2,TRUE) | E22: 4
A23: 10 | B23: Look up the pre-rebate Income Tax of EmpID #1 from the worksheet. | C23: XLOOKUP | D23: =XLOOKUP($B$5,'Tax Worksheet'!$A$5:$A$16,'Tax Worksheet'!$J$5:$J$16) | E23: 2
A24: 11 | B24: Compute Cess (4%) on EmpID #1's Tax-After-Rebate. Use XLOOKUP for the tax, ref the cess constant. | C24: XLOOKUP + ref | D24: =XLOOKUP($B$5,'Tax Worksheet'!$A$5:$A$16,'Tax Worksheet'!$L$5:$L$16)*'Tax Worksheet'!$O$23 | E24: 3
A25: 12 | B25: Find the Surcharge RATE that applies to EmpID #2's GROSS income (approximate match). | C25: XLOOKUP + VLOOKUP | D25: =VLOOKUP(XLOOKUP($B$6,'Tax Worksheet'!$A$5:$A$16,'Tax Worksheet'!$F$5:$F$16),'Tax Worksheet'!$N$16:$O$19,2,TRUE) | E25: 4
A26: 13 | B26: Two-way lookup: return the field named in B10 for EmpID #1 (e.g. B10 = "City"). | C26: INDEX + MATCH×2 | D26: =INDEX('Tax Worksheet'!$A$5:$L$16,MATCH($B$5,'Tax Worksheet'!$A$5:$A$16,0),MATCH($B$10,'Tax Worksheet'!$A$4:$L$4,0)) | E26: 4
A27: 14 | B27: Highest Gross salary in the company, then who earns it (name). | C27: MAX + INDEX/MATCH | D27: =INDEX('Tax Worksheet'!$B$5:$B$16,MATCH(MAX('Tax Worksheet'!$F$5:$F$16),'Tax Worksheet'!$F$5:$F$16,0)) | E27: 3
A28: 15 | B28: Count how many employees are in the Department in B7. | C28: COUNTIF | D28: =COUNTIF('Tax Worksheet'!$C$5:$C$16,$B$7) | E28: 2
A29: 16 | B29: Total Income Tax (pre-rebate) collected from the Finance department only. | C29: SUMIF | D29: =SUMIF('Tax Worksheet'!$C$5:$C$16,"Finance",'Tax Worksheet'!$J$5:$J$16) | E29: 3
A30: 17 | B30: Reverse lookup: find the EmpID of the employee whose Name is in B11 (e.g. "Kiara Shah"). | C30: INDEX + MATCH | D30: =INDEX('Tax Worksheet'!$A$5:$A$16,MATCH($B$11,'Tax Worksheet'!$B$5:$B$16,0)) | E30: 3
A31: 18 | B31: Approximate-grade lookup: give EmpID #2 a letter grade from the income-grade scale you build in N (or use slab label as proxy). | C31: XLOOKUP / VLOOKUP | D31: =XLOOKUP(XLOOKUP($B$6,'Tax Worksheet'!$A$5:$A$16,'Tax Worksheet'!$G$5:$G$16),$N$36:$N$39,$O$36:$O$39,,-1) | E31: 2
B32: TOTAL | E32: 50
N35: Income From (₹) | O35: Grade
N36: 0 | O36: D
N37: 500000 | O37: C
N38: 1000000 | O38: B
N39: 1500000 | O39: A
